idem_vault/conf.py
idem_vault/version.py
idem_vault/acct/backend/vault.py
idem_vault/exec/hvac/init.py
idem_vault/exec/vault/secrets/kv_v1/secret.py
idem_vault/exec/vault/secrets/kv_v2/secret.py
idem_vault/source/vault.py
idem_vault/states/vault/init.py
idem_vault/states/vault/secrets/kv_v1/key.py
idem_vault/states/vault/secrets/kv_v1/secret.py
idem_vault/states/vault/secrets/kv_v2/secret.py
idem_vault/tool/hvac/client.py
idem_vault/tool/hvac/resolve.py
idem_vault/tool/vault/secret.py
idem_vault-2.1.1.dist-info/LICENSE
idem_vault-2.1.1.dist-info/METADATA
idem_vault-2.1.1.dist-info/WHEEL
idem_vault-2.1.1.dist-info/entry_points.txt
idem_vault-2.1.1.dist-info/top_level.txt
idem_vault-2.1.1.dist-info/RECORD
