Metadata-Version: 2.1
Name: idem-vault
Version: 2.1.1
Summary: UNKNOWN
Home-page: UNKNOWN
Author: VMware Inc.
Author-email: mpeer@vmware.com
License: Apache Software License 2.0
Platform: UNKNOWN
Classifier: Environment :: Console
Classifier: Intended Audience :: Developers
Classifier: Intended Audience :: Information Technology
Classifier: Intended Audience :: System Administrators
Classifier: Operating System :: OS Independent
Classifier: Programming Language :: Python
Classifier: Programming Language :: Python :: 3.8
Classifier: Programming Language :: Python :: 3.9
Classifier: Programming Language :: Python :: 3.10
Classifier: Programming Language :: Python :: 3.11
Classifier: Development Status :: 5 - Production/Stable
Classifier: License :: OSI Approved :: Apache Software License
Requires-Python: >=3.8
License-File: LICENSE
Requires-Dist: idem >=23.0.0
Requires-Dist: hvac <1.0.0,>=0.11.2
Requires-Dist: PyYaml >=6.0.1
Requires-Dist: pop >=26.0.3
